examples/prague-cartoon.jpg
examples/prague.jpg
imfun/__init__.py
imfun/app.py
imfun/lib.py
imfun/py.typed
imfun-0.1.1.dist-info/entry_points.txt
imfun-0.1.1.dist-info/LICENSE
imfun-0.1.1.dist-info/WHEEL
imfun-0.1.1.dist-info/METADATA
imfun-0.1.1.dist-info/RECORD
