Metadata-Version: 2.1
Name: imfun
Version: 0.1.1
Summary: Convert an image to cartoon
Home-page: https://github.com/matyama/imfun
License: MIT
Keywords: image-processing,opencv,for-fun
Author: Martin Matyášek
Author-email: martin.matyasek@gmail.com
Requires-Python: >=3.8,<4.0
Classifier: Development Status :: 3 - Alpha
Classifier: Environment :: Console
Classifier: License :: OSI Approved :: MIT License
Classifier: Operating System :: Unix
Classifier: Programming Language :: Python :: 3
Classifier: Programming Language :: Python :: 3.8
Classifier: Programming Language :: Python :: 3.9
Classifier: Topic :: Multimedia
Classifier: Topic :: Multimedia :: Graphics
Classifier: Topic :: Multimedia :: Graphics :: Graphics Conversion
Classifier: Topic :: Utilities
Requires-Dist: click (>=7.1.2,<8.0.0)
Requires-Dist: numpy (>=1.19.4,<2.0.0)
Requires-Dist: opencv-python (>=4.5.1,<5.0.0)
Project-URL: Repository, https://github.com/matyama/imfun
